{
  "id": 2595,
  "slug": "223955250",
  "title": "",
  "date": "2009-10-26T09:54:00.000Z",
  "excerpt": "",
  "content": "![](https://macsfvent.sgp1.cdn.digitaloceanspaces.com/media/tumblr/tumblr_ks4sbcgn4X1qzwi7fo1_r1_400.jpg)\n\nGot an MRI for the first time today.\n\nWhatever \"signal of intensity\" and \"marginal thickening\" means, it causes me pain in the shoulder. Need to go meet the doctor one more time to see whether or not I need to have an operation. Hehe ...",
  "categories": [
    "Photo"
  ],
  "tags": [
    "health"
  ]
}