{
  "id": 431,
  "slug": "%e0%b8%ab%e0%b8%b2%e0%b8%87%e0%b8%9f%e0%b8%b2%e0%b8%94%e0%b8%ab%e0%b8%b1%e0%b8%a7-%e0%b8%ab%e0%b8%b1%e0%b8%a7%e0%b9%81%e0%b8%97%e0%b8%b0%e0%b8%ab%e0%b8%b2%e0%b8%87",
  "title": "หางฟาดหัว หัวแทะหาง",
  "date": "2003-01-09T14:48:04.000Z",
  "excerpt": "",
  "content": "สงสัยหลัง ๆ นี่คนประชาธิปัตย์จะว่าง ก็เลยเริ่มหันกลับมาแทะ ๆ เล็ม ๆ พวกเดียวกันเอง ประเด็นหลัก ๆ ก็เห็นจะมีอยู่ว่า คุณชวนควรจะเป็นหัวหน้าพรรคต่อไปรึเปล่า และใครจะเป็นหัวหน้าพรรคคนต่อไป\n\nอันที่จริงแล้ว คุณคนเขียนก็ไม่ได้ worry อะไรมากมายอะนะ ว่าใครจะเป็นหัวหน้าพรรค แต่ไอ้การหันหน้ามาคุ้ย ๆ เขียน ๆ กันเนี่ย มันทำให้คุณคนเขียนสงสัยว่า เค้าไม่มีอะไรนอกพรรคให้ไปทำกันแล้วรึยังไง ... ก็อย่างว่าหละ ตอนนี้รัฐบาลทำอะไร ใคร ๆ ก็ว่าดีไปหมด (ยกเว้นพวกไม่นิยมรัฐบาล อย่างคุณคนเขียน เป็นต้น) ฝ่ายค้านก็เลยเหมือนกับว่าว่างงาน ครั้นจะเงียบ ๆ หาย ๆ มันก็จะกะไรอยู่ เดี๋ยวประชาชนจะลืมไปซะหมด ว่านักการเมืองอีกฝั่งหนึ่งไม่ได้มีแค่ ชวน หลีกภัย คนอื่น ๆ ก็ยังมีชีวิตอยู่ ก็เลยออกมาส่งเสียงกันคนละแอะ สองแอะ พอให้คนจำได้\n\nที่น่าเห็นใจก็คงไม่พ้นคุณชวน เพราะดูหยั่งก๊ะโดนสะกิดให้ลงจากเก้าอี้ได้แล้วหยั่งไงหยั่งงั้น ... ไม่ดีเลย เสียจริง ๆ\n\n* เช้านี้ MSN ก็พังอีกแล้ว ข่าวว่าคราวที่แล้วที่พัง เกิดจากความผิดพลาดจากการ install routers .. ซึ่งจากข่าวเค้าก็บอกว่าว่า ที่ต้องเพิ่ม router ชุดใหม่ก็เพื่อ  __\"... to make the service more reliable.\"__  ... ไม่น่าเลยจริง ๆ",
  "categories": [
    "Breadcrumb"
  ],
  "tags": [
    "politics"
  ]
}