{
  "id": 4417,
  "slug": "20150208-kamakura",
  "title": "2015/02/08 ไปชมพระใหญ่ ไปชิมราเมง",
  "date": "2015-06-15T05:45:24.000Z",
  "excerpt": "",
  "content": "(2015/06/15 - เวลาผ่านไปจนเกือบจะไปญี่ปุ่นอีกรอบแล้ว ต้องรีบมาเขียนของเก่าให้เสร็จก่อน!)\r\n\r\nวันนี้อากาศไม่ค่อยดี ผิดแผนไปพอสมควร แต่ความสนุกและการผจญภัยไม่ได้ลดลงเลย! (ขึ้นหัวเรื่องราวกับการ์ตูน)\r\n\r\nตื่นเช้าหาอะไรรองท้องนิดหน่อย แล้วออกเดินทางไปเมือง Kamakura ซึ่งโดยปกติสามารถนั่ง JR ไปได้เลย (ผ่าน Yokohama) ใช้เวลาไม่น่าเกิน 1 ชั่วโมงก็น่าจะถึง แต่เลือกเดินทางแบบอ้อมนิดหน่อย เพื่อลองระบบการขนส่งที่หลากหลายของญี่ปุ่น\r\n\r\n![](https://macsfvent.sgp1.cdn.digitaloceanspaces.com/media/2015/06/japan_2015_100.jpg)\r\n\r\n![](https://macsfvent.sgp1.cdn.digitaloceanspaces.com/media/2015/06/japan_2015_101.jpg)\r\n\r\nเริ่มจากเดินทางด้วย JR จาก Ueno ไปเปลี่ยนรถที่สถานี Tokyo ปลายทางที่ Ofuna แล้วเดินทางด้วย Shonan Monorail ต่อไปลงที่สถานี Shonan-enoshima แล้วเดินนิดหน่อยไปที่สถานี Enoshima เพี่อนั่ง Enoshima Electric Railway ไปลงที่สถานี Hase ซึ่งอยู่ไม่ห่างจากบริเวณพระใหญ่ (Great Buddha หรือ Daibutsu) เท่าไหร่นัก\r\n\r\n![](https://macsfvent.sgp1.cdn.digitaloceanspaces.com/media/2015/06/japan_2015_102.jpg)\r\n\r\n![](https://macsfvent.sgp1.cdn.digitaloceanspaces.com/media/2015/06/japan_2015_103.jpg)\r\n\r\n![](https://macsfvent.sgp1.cdn.digitaloceanspaces.com/media/2015/06/japan_2015_104.jpg)\r\n\r\n![](https://macsfvent.sgp1.cdn.digitaloceanspaces.com/media/2015/06/japan_2015_105.jpg)\r\n\r\n![](https://macsfvent.sgp1.cdn.digitaloceanspaces.com/media/2015/06/japan_2015_106.jpg)\r\n\r\n(ถ้านั่ง JR ตรงไปลง Kamakura เลย ก็นั่งรถเมล์สาย 2 หรือ 4 ไปลงตรงหน้าวัดพอดี)\r\n\r\nเมือง Kamakura เป็นเมืองเล็ก ๆ ที่ระหว่างทางมีร้านรวงน่ารักน่าถ่ายรูป บ้านเรือนแบบเก่า ๆ อยู่พอสมควรชแต่ด้วยความที่ฝนตกแรงพอควร และอากาศก็หนาวเย็นเหลือเกิน เดินกันไม่ค่อยสนุกเท่าไหร่ แวะได้แค่ Hase Dera กับ Daibutsu ก็ยอมแพ้ ขอย้ายไปกินราเมงดีกว่า\r\n\r\n![](https://macsfvent.sgp1.cdn.digitaloceanspaces.com/media/2015/06/japan_2015_107.jpg)\r\n\r\n![](https://macsfvent.sgp1.cdn.digitaloceanspaces.com/media/2015/06/japan_2015_108.jpg)\r\n\r\n![](https://macsfvent.sgp1.cdn.digitaloceanspaces.com/media/2015/06/japan_2015_109.jpg)\r\n\r\n![](https://macsfvent.sgp1.cdn.digitaloceanspaces.com/media/2015/06/japan_2015_110.jpg)\r\n\r\n![](https://macsfvent.sgp1.cdn.digitaloceanspaces.com/media/2015/06/japan_2015_111.jpg)\r\n\r\n![](https://macsfvent.sgp1.cdn.digitaloceanspaces.com/media/2015/06/japan_2015_112.jpg)\r\n\r\n![](https://macsfvent.sgp1.cdn.digitaloceanspaces.com/media/2015/06/japan_2015_113.jpg)\r\n\r\n![](https://macsfvent.sgp1.cdn.digitaloceanspaces.com/media/2015/06/japan_2015_114.jpg)\r\n\r\n![](https://macsfvent.sgp1.cdn.digitaloceanspaces.com/media/2015/06/japan_2015_115.jpg)\r\n\r\n\r\nนั่งรถเมล์จากหน้าวัดไปลงที่สถานี Kamakura แล้วนั่ง JR ไปลงที่ Yokohama แล้วเปลี่ยนรถไปลงที่ Shin-Yokohama จะนั่ง JR หรือใช้ Blue Line Subway ของ Yokohama ก็ได้ ขึ้นจากสถานีมาแล้วเดินนิดหน่อยก็ถึง Ramen Museum \r\n\r\n![](https://macsfvent.sgp1.cdn.digitaloceanspaces.com/media/2015/06/japan_2015_116.jpg)\r\n\r\nจริง ๆ Ramen Museum ก็ไม่ได้เป็น \"พิพิธภัณฑ์\" อะไรนะ เป็นเหมือนที่รวมร้านขายราเมงดัง ๆ แล้วแต่งให้ข้างในดูเก่า ๆ โบราณ ๆ คนไปกินราเมงเยอะมาก\r\n\r\n![](https://macsfvent.sgp1.cdn.digitaloceanspaces.com/media/2015/06/japan_2015_117.jpg)\r\n\r\nถ้าอยากชิมราเมงหลาย ๆ ร้าน จากหลาย ๆ จังหวัด ไปที่นี่ดีเลย แต่ถ้าไม่ซีเรียส กินราเมงตามสถานีรถไฟก็ได้ อร่อยเหมือนกัน\r\n\r\nตามแผนเดิม ออกจาก Ramen Museum ก็จะนั่งรถย้อนกลับ Yokohama เพื่อเข้าไปเที่ยวในเมือง รวมถึงแวะไป Chinatown ของเขาสักหน่อย แต่ยอมแพ้อากาศ ไปต่อไม่ไหว ฝากไว้คราวหน้าถ้ามีโอกาสมาอีกก็แล้วกัน ตัดสินใจนั่งรถกลับเข้า Shibuya เดินดูนู่นดูนี่ แวะดู supermarket แล้วกลับมาเก็บกระเป๋าที่โรงแรม\r\n",
  "categories": [
    "General"
  ],
  "tags": [
    "Japan",
    "trip",
    "Japan Trip 2015",
    "kamakura",
    "yokohama",
    "ramen museum",
    "daibutsu",
    "hase dera"
  ]
}