{
  "id": 1277,
  "slug": "1277",
  "title": "เรื่องมาก ไร้สาระ",
  "date": "2008-02-07T08:45:47.000Z",
  "excerpt": "",
  "content": "คุณคนเขียนขอบ่นเรื่องไม่เป็นเรื่องสักหน่อยละกันนะครับ ... เอาแบบสั้น ๆ นะ\n\nคุณคนเขียนวางแผนว่าจะเดินทางไปอิตาลีช่วงปลาย ๆ เดือนเมษายน ก็เลยต้องจัดเตรียมเอกสารสำหรับการขอวีซ่าเพื่อเดินทางเข้ายุโรป หนึ่งในนั้นคือ \"หนังสือรับรองสถานะการเงิน\"\n\nครั้งแรก คุณคนเขียนไปที่ธนาคารใกล้ ๆ บ้าน ได้รับคำตอบมาว่า \"ต้องไปขอจากธนาคารที่เปิดบัญชีเท่านั้น\" ... พนักงานไม่สามารถให้เหตุผลได้ว่า \"ทำไม\"\n\nครั้งที่สอง คุณคนเขียนไปที่ \"สาขาที่เปิดบัญชี\" พอบอกว่าต้องการขอ \"financial statement\" พนักงานถามว่า \"financial statement หรือ หนังสือรับรองสถานะการเงิน คะ?\" คุณคนเขียนสงสัยว่า มันต่างกันด้วยเหรอ? พอยื่นสมุดบัญชีพร้อมบัตรประชาชนให้ พนักงานบอกว่า \"ต้องใช้ passport ด้วยนะคะ\" พอถามเหตุผลก็ได้คำตอบว่า \"ต้องสะกดชื่อให้ตรงกับ passport\" ... เขียนให้ก็ไม่ได้ ต้องดูจาก passport เท่านั้น\n\n... แค่ขอจดหมายบอกว่ามีสะตังพอไปเที่ยวได้ ทำอย่างกับว่าจะขนเงินออกนอกประเทศ หรือเพราะว่ามีสะตังไม่ถึงเจ็ดหมื่นสามพันล้าน?\n\nสรุปว่า ถ้าจะขอหนังสือรับรองสถานะการเงิน หรือที่รู้จักกันทั่วไปว่า financial statement (ยกเว้นพนักงานธนาคารสาขาที่คุณคนเขียนเปิดบัญชี) จะต้องเดินทางไปธนาคารสาขาที่เปิดบัญชีเอาไว้ โดยใช้สมุดบัญชีเล่มที่ต้องการให้รับรอง บัตรประชาชน และหนังสือเดินทาง พร้อมเงิน 100 บาทครับ!!!\n\nคิดซะว่า จะได้ไปหานักบุญเปโตรถึงที่ ก็ต้องลำบากกันหน่อยก็แล้วกันครับ -\"-",
  "categories": [
    "Breadcrumb"
  ],
  "tags": [
    "rant"
  ]
}