{
  "id": 3791,
  "slug": "3791",
  "title": "",
  "date": "2013-04-22T19:07:53.000Z",
  "excerpt": "",
  "content": "<img src=\"https://macsfvent.sgp1.cdn.digitaloceanspaces.com/media/2013/09/tumblr_mlpuvbHunG1rlfwkuo1_1280.jpg\" alt=\"tumblr_mlpuvbHunG1rlfwkuo1_1280\" width=\"612\" height=\"612\" class=\"alignnone size-full wp-image-3792\" />\n\nAnd there's #1 and #2. #2 will now become the home server and #1 will run XBMC. (I shamefully keep #3 for an unknown future project.)",
  "categories": [
    "General"
  ],
  "tags": []
}