{
  "id": 4715,
  "slug": "a-creed",
  "title": "A Creed",
  "date": "2016-04-07T02:01:50.000Z",
  "excerpt": "",
  "content": "Let me be a little kinder,   \r\nLet me be a little blinder   \r\nTo the faults of those around me,   \r\nLet me praise a little more;   \r\nLet me be, when I am weary   \r\nJust a little bit more cheery,   \r\nLet me serve a little better   \r\nThose that I am striving for.   \r\n\r\nLet me be a little braver  \r\nWhen temptation bids me waver,  \r\nLet me strive a little harder  \r\nTo be all that I should be;  \r\nLet me be a little meeker  \r\nWith the brother that is weaker,  \r\nLet me think more of my neighbor  \r\nAnd a little less of me.  \r\n\r\nLet me be a little sweeter,   \r\nMake my life a bit completer   \r\nBy doing what I should do   \r\nEvery minute of the day;   \r\nLet me toil, without complaining,   \r\nNot a humble task disdaining,   \r\nLet me face the summons calmly   \r\nWhen death beckons me away.  \r\n\r\n-- Edgar A. Guest (A Creed)",
  "categories": [
    "General"
  ],
  "tags": []
}