{
  "id": 1227,
  "slug": "another-kind-of-cat",
  "title": "Another Kind of Cat",
  "date": "2007-10-29T01:57:23.000Z",
  "excerpt": "",
  "content": "Actually, they're real cat, two of them -- the mother and the kitten.\n\nI've seen the mother cat walking around for quite a while already. Actually, she had one kitten back in August.\n\n![](https://macsfvent.sgp1.cdn.digitaloceanspaces.com/media/2007/10/cat_kitten_01.jpg)\n\nCut back to present time, she just had another kitten. The little cat is still very tiny.\n\n![](https://macsfvent.sgp1.cdn.digitaloceanspaces.com/media/2007/10/cat_kitten_02.jpg)\n\nThe mother cat doesn't really want to be friend with me when she doesn't have kitten. So I don't think she is in the mood to get to know me right now.\n\nAdorable, don't you think?",
  "categories": [
    "Breadcrumb"
  ],
  "tags": [
    "random thoughts"
  ]
}